[
	{
		"__TYPE__": "SharedSliceContent",
		"variation": "image_left_content_right",
		"primary": {
			"media": {
				"__TYPE__": "ImageContent",
				"origin": {
					"id": "main",
					"url": "https://images.unsplash.com/photo-1471897488648-5eae4ac6686b",
					"width": 3560,
					"height": 5340
				},
				"url": "https://images.unsplash.com/photo-1471897488648-5eae4ac6686b",
				"width": 3560,
				"height": 5340,
				"edit": {
					"zoom": 1,
					"crop": {
						"x": 0,
						"y": 0
					},
					"background": "transparent"
				},
				"alt": "claws"
			},
			"pretitle": {
				"__TYPE__": "StructuredTextContent",
				"value": [
					{
						"type": "paragraph",
						"content": {
							"text": "Nisi reprehenderit quis eiusmod duis irure adipisicing non ullamco fugiat commodo enim officia."
						}
					}
				]
			},
			"title": {
				"__TYPE__": "StructuredTextContent",
				"value": [
					{
						"type": "heading1",
						"content": {
							"text": "Growth"
						}
					}
				]
			},
			"subtitle": {
				"__TYPE__": "StructuredTextContent",
				"value": [
					{
						"type": "heading3",
						"content": {
							"text": "Activity"
						}
					}
				]
			},
			"info_blocks": {
				"__TYPE__": "GroupContentType",
				"value": [
					{
						"__TYPE__": "GroupItemContent",
						"value": [
							[
								"block_title",
								{
									"__TYPE__": "StructuredTextContent",
									"value": [
										{
											"type": "heading4",
											"content": {
												"text": "Freedom"
											}
										}
									]
								}
							],
							[
								"block_content",
								{
									"__TYPE__": "StructuredTextContent",
									"value": [
										{
											"type": "paragraph",
											"content": {
												"text": "Nostrud enim velit aute dolore esse enim ad Lorem anim in amet voluptate id excepteur. Duis nulla dolor nulla commodo laborum veniam occaecat do pariatur pariatur aute nisi adipisicing."
											}
										}
									]
								}
							]
						]
					}
				]
			}
		},
		"items": []
	}
]